jaraco/home/Gather HDHomeRun Stats.plist
jaraco/home/__init__.py
jaraco/home/check-traps.py
jaraco/home/contact.py
jaraco/home/hdhomerun.py
jaraco/home/mock hdhomerun.py
jaraco/home/relay.py
jaraco/home/report-spam-call.py
jaraco/home/thermostat.py
jaraco/home/compat/__init__.py
jaraco/home/compat/py38.py
jaraco.home-3.10.2.dist-info/LICENSE
jaraco.home-3.10.2.dist-info/METADATA
jaraco.home-3.10.2.dist-info/WHEEL
jaraco.home-3.10.2.dist-info/top_level.txt
jaraco.home-3.10.2.dist-info/RECORD
