Metadata-Version: 2.1
Name: jaraco.home
Version: 3.10.2
Summary: Some functions supporting the devices in jaraco's home
Author-email: "Jason R. Coombs" <jaraco@jaraco.com>
Project-URL: Source, https://github.com/jaraco/jaraco.home
Classifier: Development Status :: 5 - Production/Stable
Classifier: Intended Audience :: Developers
Classifier: License :: OSI Approved :: MIT License
Classifier: Programming Language :: Python :: 3
Classifier: Programming Language :: Python :: 3 :: Only
Requires-Python: >=3.8
License-File: LICENSE
Requires-Dist: requests
Requires-Dist: lxml >=4.2.6
Requires-Dist: pymongo
Requires-Dist: jaraco.functools
Requires-Dist: jaraco.mongodb
Requires-Dist: dnspython
Requires-Dist: keyring
Requires-Dist: jaraco.collections
Requires-Dist: splinter[selenium]
Requires-Dist: autocommand
Requires-Dist: python-dateutil
Requires-Dist: victor-smart-kill
Requires-Dist: jaraco.compat >=4.1
Requires-Dist: tempora >=5.7
Requires-Dist: importlib-resources ; python_version < "3.9"
Provides-Extra: doc
Requires-Dist: sphinx >=3.5 ; extra == 'doc'
Requires-Dist: jaraco.packaging >=9.3 ; extra == 'doc'
Requires-Dist: rst.linker >=1.9 ; extra == 'doc'
Requires-Dist: furo ; extra == 'doc'
Requires-Dist: sphinx-lint ; extra == 'doc'
Provides-Extra: test
Requires-Dist: pytest !=8.1.*,>=6 ; extra == 'test'
Requires-Dist: pytest-checkdocs >=2.4 ; extra == 'test'
Requires-Dist: pytest-cov ; extra == 'test'
Requires-Dist: pytest-mypy ; extra == 'test'
Requires-Dist: pytest-enabler >=2.2 ; extra == 'test'
Requires-Dist: types-requests ; extra == 'test'
Requires-Dist: mockproc ; extra == 'test'
Requires-Dist: types-python-dateutil ; extra == 'test'
Requires-Dist: pytest-ruff >=0.2.1 ; (sys_platform != "cygwin") and extra == 'test'
